[{"inputs":[{"components":[{"internalType":"address","name":"admin","type":"address"},{"internalType":"address","name":"emergencyAdmin","type":"address"},{"internalType":"address","name":"paymentAdmin","type":"address"},{"internalType":"address","name":"csrProcessor","type":"address"},{"internalType":"address","name":"tlProcessor","type":"address"},{"internalType":"address","name":"brProcessor","type":"address"},{"internalType":"address","name":"csrUpdater","type":"address"},{"internalType":"address","name":"srcVaaRelayer","type":"address"},{"internalType":"address","name":"dstSwapper","type":"address"},{"internalType":"address","name":"csrRescuer","type":"address"},{"internalType":"address","name":"csrDisputer","type":"address"}],"internalType":"struct ISuperRBAC.InitialRoleSetup","name":"roles","type":"tuple"}],"stateMutability":"nonpayable","type":"constructor"},{"inputs":[],"name":"AccessControlBadConfirmation","type":"error"},{"inputs":[{"internalType":"address","name":"account","type":"address"},{"internalType":"bytes32","name":"neededRole","type":"bytes32"}],"name":"AccessControlUnauthorizedAccount","type":"error"},{"inputs":[],"name":"CANNOT_REVOKE_LAST_ADMIN","type":"error"},{"inputs":[],"name":"CANNOT_REVOKE_NON_BROADCASTABLE_ROLES","type":"error"},{"inputs":[],"name":"DISABLED","type":"error"},{"inputs":[],"name":"FAILED_TO_SEND_NATIVE","type":"error"},{"inputs":[],"name":"INVALID_BROADCAST_FEE","type":"error"},{"inputs":[],"name":"INVALID_MESSAGE_TYPE","type":"error"},{"inputs":[],"name":"NOT_BROADCAST_REGISTRY","type":"error"},{"inputs":[],"name":"ROLE_NOT_ASSIGNED","type":"error"},{"inputs":[],"name":"ZERO_ADDRESS","type":"error"},{"anonymous":false,"inputs":[{"indexed":true,"internalType":"bytes32","name":"role","type":"bytes32"},{"indexed":true,"internalType":"bytes32","name":"previousAdminRole","type":"bytes32"},{"indexed":true,"internalType":"bytes32","name":"newAdminRole","type":"bytes32"}],"name":"RoleAdminChanged","type":"event"},{"anonymous":false,"inputs":[{"indexed":false,"internalType":"bytes32","name":"role","type":"bytes32"},{"indexed":false,"internalType":"bytes32","name":"adminRole","type":"bytes32"}],"name":"RoleAdminSet","type":"event"},{"anonymous":false,"inputs":[{"indexed":true,"internalType":"bytes32","name":"role","type":"bytes32"},{"indexed":true,"internalType":"address","name":"account","type":"address"},{"indexed":true,"internalType":"address","name":"sender","type":"address"}],"name":"RoleGranted","type":"event"},{"anonymous":false,"inputs":[{"indexed":true,"internalType":"bytes32","name":"role","type":"bytes32"},{"indexed":true,"internalType":"address","name":"account","type":"address"},{"indexed":true,"internalType":"address","name":"sender","type":"address"}],"name":"RoleRevoked","type":"event"},{"anonymous":false,"inputs":[{"indexed":true,"internalType":"address","name":"superRegistry","type":"address"}],"name":"SuperRegistrySet","type":"event"},{"inputs":[],"name":"BROADCASTER_ROLE","outputs":[{"internalType":"bytes32","name":"","type":"bytes32"}],"stateMutability":"view","type":"function"},{"inputs":[],"name":"BROADCAST_STATE_REGISTRY_PROCESSOR_ROLE","outputs":[{"internalType":"bytes32","name":"","type":"bytes32"}],"stateMutability":"view","type":"function"},{"inputs":[],"name":"CORE_STATE_REGISTRY_DISPUTER_ROLE","outputs":[{"internalType":"bytes32","name":"","type":"bytes32"}],"stateMutability":"view","type":"function"},{"inputs":[],"name":"CORE_STATE_REGISTRY_PROCESSOR_ROLE","outputs":[{"internalType":"bytes32","name":"","type":"bytes32"}],"stateMutability":"view","type":"function"},{"inputs":[],"name":"CORE_STATE_REGISTRY_RESCUER_ROLE","outputs":[{"internalType":"bytes32","name":"","type":"bytes32"}],"stateMutability":"view","type":"function"},{"inputs":[],"name":"CORE_STATE_REGISTRY_UPDATER_ROLE","outputs":[{"internalType":"bytes32","name":"","type":"bytes32"}],"stateMutability":"view","type":"function"},{"inputs":[],"name":"DEFAULT_ADMIN_ROLE","outputs":[{"internalType":"bytes32","name":"","type":"bytes32"}],"stateMutability":"view","type":"function"},{"inputs":[],"name":"DST_SWAPPER_ROLE","outputs":[{"internalType":"bytes32","name":"","type":"bytes32"}],"stateMutability":"view","type":"function"},{"inputs":[],"name":"EMERGENCY_ADMIN_ROLE","outputs":[{"internalType":"bytes32","name":"","type":"bytes32"}],"stateMutability":"view","type":"function"},{"inputs":[],"name":"PAYMENT_ADMIN_ROLE","outputs":[{"internalType":"bytes32","name":"","type":"bytes32"}],"stateMutability":"view","type":"function"},{"inputs":[],"name":"PROTOCOL_ADMIN_ROLE","outputs":[{"internalType":"bytes32","name":"","type":"bytes32"}],"stateMutability":"view","type":"function"},{"inputs":[],"name":"SYNC_REVOKE","outputs":[{"internalType":"bytes32","name":"","type":"bytes32"}],"stateMutability":"view","type":"function"},{"inputs":[],"name":"TIMELOCK_STATE_REGISTRY_PROCESSOR_ROLE","outputs":[{"internalType":"bytes32","name":"","type":"bytes32"}],"stateMutability":"view","type":"function"},{"inputs":[],"name":"WORMHOLE_VAA_RELAYER_ROLE","outputs":[{"internalType":"bytes32","name":"","type":"bytes32"}],"stateMutability":"view","type":"function"},{"inputs":[{"internalType":"bytes32","name":"role","type":"bytes32"}],"name":"getRoleAdmin","outputs":[{"internalType":"bytes32","name":"","type":"bytes32"}],"stateMutability":"view","type":"function"},{"inputs":[{"internalType":"bytes32","name":"role","type":"bytes32"},{"internalType":"uint256","name":"index","type":"uint256"}],"name":"getRoleMember","outputs":[{"internalType":"address","name":"","type":"address"}],"stateMutability":"view","type":"function"},{"inputs":[{"internalType":"bytes32","name":"role","type":"bytes32"}],"name":"getRoleMemberCount","outputs":[{"internalType":"uint256","name":"","type":"uint256"}],"stateMutability":"view","type":"function"},{"inputs":[{"internalType":"bytes32","name":"role","type":"bytes32"},{"internalType":"address","name":"account","type":"address"}],"name":"grantRole","outputs":[],"stateMutability":"nonpayable","type":"function"},{"inputs":[{"internalType":"address","name":"emergencyAdmin_","type":"address"}],"name":"hasEmergencyAdminRole","outputs":[{"internalType":"bool","name":"","type":"bool"}],"stateMutability":"view","type":"function"},{"inputs":[{"internalType":"address","name":"admin_","type":"address"}],"name":"hasProtocolAdminRole","outputs":[{"internalType":"bool","name":"","type":"bool"}],"stateMutability":"view","type":"function"},{"inputs":[{"internalType":"bytes32","name":"role","type":"bytes32"},{"internalType":"address","name":"account","type":"address"}],"name":"hasRole","outputs":[{"internalType":"bool","name":"","type":"bool"}],"stateMutability":"view","type":"function"},{"inputs":[{"internalType":"bytes32","name":"role","type":"bytes32"},{"internalType":"address","name":"callerConfirmation","type":"address"}],"name":"renounceRole","outputs":[],"stateMutability":"nonpayable","type":"function"},{"inputs":[{"internalType":"bytes32","name":"role","type":"bytes32"},{"internalType":"address","name":"account","type":"address"}],"name":"revokeRole","outputs":[],"stateMutability":"nonpayable","type":"function"},{"inputs":[{"internalType":"bytes32","name":"role_","type":"bytes32"},{"internalType":"bytes","name":"extraData_","type":"bytes"},{"internalType":"bytes32","name":"superRegistryAddressId_","type":"bytes32"}],"name":"revokeRoleSuperBroadcast","outputs":[],"stateMutability":"payable","type":"function"},{"inputs":[{"internalType":"bytes32","name":"role_","type":"bytes32"},{"internalType":"bytes32","name":"adminRole_","type":"bytes32"}],"name":"setRoleAdmin","outputs":[],"stateMutability":"nonpayable","type":"function"},{"inputs":[{"internalType":"address","name":"superRegistry_","type":"address"}],"name":"setSuperRegistry","outputs":[],"stateMutability":"nonpayable","type":"function"},{"inputs":[{"internalType":"bytes","name":"data_","type":"bytes"}],"name":"stateSyncBroadcast","outputs":[],"stateMutability":"nonpayable","type":"function"},{"inputs":[],"name":"superRegistry","outputs":[{"internalType":"contract ISuperRegistry","name":"","type":"address"}],"stateMutability":"view","type":"function"},{"inputs":[{"internalType":"bytes4","name":"interfaceId","type":"bytes4"}],"name":"supportsInterface","outputs":[{"internalType":"bool","name":"","type":"bool"}],"stateMutability":"view","type":"function"},{"inputs":[],"name":"xChainPayloadCounter","outputs":[{"internalType":"uint256","name":"","type":"uint256"}],"stateMutability":"view","type":"function"}]